asgi.py
asgi/__init__.py
asgi/py.typed
workers/__init__.py
workers/_workers.py
workers/py.typed
workers/workflows.py
python_workers_runtime_sdk-0.1.0.dist-info/METADATA
python_workers_runtime_sdk-0.1.0.dist-info/WHEEL
python_workers_runtime_sdk-0.1.0.dist-info/RECORD
