Metadata-Version: 2.4
Name: python-workers-runtime-sdk
Version: 0.1.0
Summary: sdk for Cloudflare Python Workers runtime
Requires-Python: >=3.12
